ydl_podcast/__init__.py
ydl_podcast/__main__.py
ydl_podcast/templates/episode_nfo.py
ydl_podcast/templates/feed.py
ydl_podcast/templates/index.py
ydl_podcast/templates/show_nfo.py
ydl_podcast/templates/style.py
ydl_podcast-1.10.1.dist-info/WHEEL
ydl_podcast-1.10.1.dist-info/entry_points.txt
ydl_podcast-1.10.1.dist-info/METADATA
ydl_podcast-1.10.1.dist-info/RECORD
