Metadata-Version: 2.3
Name: ydl-podcast
Version: 1.10.1
Summary: A simple tool to generate Podcast-like RSS feeds from youtube (or other youtube-dl supported services) channels, using youtube-dl/yt-dlp
Keywords: podcast,youtube-dl
Author: nbr23
Author-email: nbr23 <max@23.tf>
License: MIT
Requires-Dist: yt-dlp>=2026.1.29
Requires-Dist: pyyaml==6.0.2
Requires-Dist: jinja2>=3.1.2
Requires-Dist: markupsafe>=2.1.1
Requires-Dist: pillow==12.0.0
Requires-Dist: youtube-dl ; extra == 'youtube-dl'
Requires-Dist: yt-dlp>=2026.1.29 ; extra == 'yt-dlp'
Requires-Python: >=3.9
Project-URL: homepage, https://github.com/nbr23/ydl-podcast
Project-URL: repository, https://github.com/nbr23/ydl-podcast
Provides-Extra: youtube-dl
Provides-Extra: yt-dlp
